README.md
README.rst
setup.py
ctpbee_analyzer/__init__.py
ctpbee_analyzer/cost.py
ctpbee_analyzer.egg-info/PKG-INFO
ctpbee_analyzer.egg-info/SOURCES.txt
ctpbee_analyzer.egg-info/dependency_links.txt
ctpbee_analyzer.egg-info/requires.txt
ctpbee_analyzer.egg-info/top_level.txt
test/test.py
test/test2.py
test/test3.py