Metadata-Version: 1.1
Name: ctpbee-analyzer
Version: 0.0.6
Summary: ctpbee_analyzer
Home-page: https://github.com/ctpbee/ctpbee_analyzer
Author: faithforus
Author-email: ljunf817@163.com
License: UNKNOWN
Keywords: python package ctpbee
Platform: UNKNOWN
Classifier: Programming Language :: Python :: 3
Classifier: License :: OSI Approved :: MIT License
Classifier: Operating System :: OS Independent
